fw_gear_dicom_splitter/__init__.py
fw_gear_dicom_splitter/geometry.py
fw_gear_dicom_splitter/main.py
fw_gear_dicom_splitter/metadata.py
fw_gear_dicom_splitter/parser.py
fw_gear_dicom_splitter/splitters.py
fw_gear_dicom_splitter/utils.py
fw_gear_dicom_splitter/dicom_splitter/__init__.py
fw_gear_dicom_splitter/dicom_splitter/base.py
fw_gear_dicom_splitter-2.1.2.dist-info/METADATA
fw_gear_dicom_splitter-2.1.2.dist-info/WHEEL
fw_gear_dicom_splitter-2.1.2.dist-info/licenses/LICENSE
fw_gear_dicom_splitter-2.1.2.dist-info/RECORD
