Metadata-Version: 2.4
Name: fw-gear-dicom-splitter
Version: 2.1.2
Summary: DICOM splitter based on unique tags, or localizers
Author-email: Flywheel <support@flywheel.io>
License-Expression: MIT
License-File: LICENSE
Requires-Python: <4,>=3.11
Requires-Dist: flywheel-gear-toolkit<0.7,>=0.6.18
Requires-Dist: flywheel-sdk<19,>=18
Requires-Dist: fw-file<5,>=4.0.0
Requires-Dist: pandas<3,>=2
Requires-Dist: pylibjpeg-libjpeg<3,>=2
Requires-Dist: pylibjpeg-openjpeg<3,>=2
Requires-Dist: pylibjpeg<3,>=2
Requires-Dist: scipy<2,>=1
